{
  "version": "7",
  "dialect": "postgresql",
  "entries": [
    {
      "idx": 0,
      "version": "7",
      "when": 1731777433008,
      "tag": "20241116171713_slimy_justice",
      "breakpoints": true
    },
    {
      "idx": 1,
      "version": "7",
      "when": 1731833735294,
      "tag": "20241117085535_strong_turbo",
      "breakpoints": true
    },
    {
      "idx": 2,
      "version": "7",
      "when": 1731833835030,
      "tag": "20241117085715_common_orphan",
      "breakpoints": true
    }
  ]
}